{"code":0,"message":"0","ttl":1,"data":{"seid":"3102866244044920675","page":1,"pagesize":20,"numResults":1000,"numPages":50,"suggest_keyword":"","rqt_type":"search","cost_time":{"total":"0.207666","fetch_lexicon":"0.004980","params_check":"0.001425","is_risk_query":"0.000128","illegal_handler":"0.000009","main_handler":"0.199821","as_request_format":"0.000891","as_request":"0.196207","deserialize_response":"0.000211","as_response_format":"0.002435"},"exp_list":{"5515":true,"6604":true,"7700":true,"9902":true,"9924":true,"9931":true,"9948":true,"9961":true,"100203":true,"100801":true,"101002":true,"101500":true,"101901":true,"102003":true,"102405":true,"102501":true,"102601":true,"102701":true,"102803":true,"102902":true,"103000":true,"103104":true,"103200":true,"103301":true},"egg_hit":0,"pageinfo":{"video":{"total":1000,"numResults":1000,"pages":50},"bangumi":{"total":0,"numResults":0,"pages":0},"special":{"total":0,"numResults":0,"pages":0},"topic":{"total":0,"numResults":0,"pages":0},"upuser":{"total":0,"numResults":0,"pages":0},"tv":{"total":0,"numResults":0,"pages":0},"movie":{"total":0,"numResults":0,"pages":0},"media_bangumi":{"total":0,"numResults":0,"pages":0},"media_ft":{"total":0,"numResults":0,"pages":0},"related_search":{"total":0,"numResults":0,"pages":0},"user":{"total":0,"numResults":0,"pages":0},"activity":{"total":0,"numResults":0,"pages":0},"operation_card":{"total":0,"numResults":0,"pages":0},"pgc":{"total":0,"numResults":0,"pages":0},"live":{"total":0,"numResults":0,"pages":0},"live_all":{"total":0,"numResults":0,"pages":0},"live_room":{"total":0,"numResults":0,"pages":0},"live_user":{"total":0,"numResults":0,"pages":0},"live_master":{"total":0,"numResults":0,"pages":0},"bili_user":{"total":0,"numResults":0,"pages":0},"article":{"total":207,"numResults":207,"pages":11}},"top_tlist":{"video":1000,"bangumi":0,"special":0,"topic":0,"upuser":0,"tv":0,"movie":0,"card":0,"media_bangumi":0,"media_ft":0,"pgc":0,"live":0,"user":0,"activity":0,"operation_card":0,"live_room":0,"live_user":0,"live_master":0,"bili_user":0,"article":207},"show_column":0,"show_module_list":["tips","brand_ad","esports","activity","web_game","card","media_bangumi","media_ft","bili_user","user","star","video"],"app_display_option":{"is_search_page_grayed":0},"in_black_key":0,"in_white_key":0,"result":[{"result_type":"tips","data":[]},{"result_type":"brand_ad","data":[]},{"result_type":"esports","data":[]},{"result_type":"activity","data":[]},{"result_type":"web_game","data":[]},{"result_type":"card","data":[]},{"result_type":"media_bangumi","data":[]},{"result_type":"media_ft","data":[]},{"result_type":"bili_user","data":[]},{"result_type":"user","data":[]},{"result_type":"star","data":[]},{"result_type":"video","data":[{"type":"video","id":657057101,"author":"tonyncl","mid":2782457,"typeid":"136","typename":"音游","arcurl":"http://www.bilibili.com/video/av657057101","aid":657057101,"bvid":"BV19h4y197Gm","title":"【\u003cem class=\"keyword\"\u003emaimai\u003c/em\u003e】\u003cem class=\"keyword\"\u003e吸血鬼\u003c/em\u003e 白谱 Lv.13 AP手元（\u003cem class=\"keyword\"\u003eヴァンパイア\u003c/em\u003e Re:MASTER ALL PERFECT）","description":"好听儿歌\n\n出勤地点：上海朗玩Round1\n速度：7\n延迟：0\n判定表示：2-E(从今天开始2杠E！！！）","arcrank":"0","pic":"//i1.hdslb.com/bfs/archive/1993cfd1d77da246a1c71bfed56d0d28f637c6f6.jpg","play":4818,"video_review":0,"favorites":70,"tag":"SEGA,街机,音乐游戏,AP,MAIMAI,舞萌,音游,舞萌DX","review":7,"pubdate":1686257691,"senddate":1686332297,"duration":"2:40","badgepay":false,"hit_columns":["title","tag"],"view_type":"","is_pay":0,"is_union_video":0,"rec_tags":null,"new_rec_tags":[],"rank_score":200000000,"like":119,"upic":"https://i2.hdslb.com/bfs/face/5ed6b3694b2e6a62369f1ebb4499a8fa71712598.jpg","corner":"","cover":"","desc":"","url":"","rec_reason":"","danmaku":0,"biz_data":null,"is_charge_video":0,"vt":0,"enable_vt":0,"vt_display":"","subtitle":"","episode_count_text":"","release_status":0,"is_intervene":0},{"type":"video","id":239349545,"author":"Maybe_Somnus","mid":18139783,"typeid":"136","typename":"音游","arcurl":"http://www.bilibili.com/video/av239349545","aid":239349545,"bvid":"BV1Ye411h78Y","title":"【\u003cem class=\"keyword\"\u003e舞萌\u003c/em\u003eDX2023/红转紫入门】让我吸一下没关系的吧？ \u003cem class=\"keyword\"\u003eヴァンパイア\u003c/em\u003e master 紫谱 附个人拆谱","description":"纯净版手元指路：BV1WC4y1k76K\n主播比较菜，做一些红转紫入门星星的拆谱！\n欢迎点星星歌！\n希望能够帮到弱底力的舞萌吃！","arcrank":"0","pic":"//i2.hdslb.com/bfs/archive/e288191f718cc6f9ad483f1d3b2032f8ca489e1a.jpg","play":1859,"video_review":1,"favorites":41,"tag":"DECO*27,音乐游戏,MAIMAI,舞萌,ヴァンパイア,玩音游玩的,红转紫","review":28,"pubdate":1706329584,"senddate":1706329584,"duration":"3:8","badgepay":false,"hit_columns":["title","description","tag"],"view_type":"","is_pay":0,"is_union_video":0,"rec_tags":null,"new_rec_tags":[],"rank_score":118723981,"like":103,"upic":"https://i1.hdslb.com/bfs/face/c8d76905d975adfdc97944e1a3b5b6f68428ced5.jpg","corner":"","cover":"","desc":"","url":"","rec_reason":"","danmaku":1,"biz_data":null,"is_charge_video":0,"vt":0,"enable_vt":0,"vt_display":"","subtitle":"","episode_count_text":"","release_status":0,"is_intervene":0},{"type":"video","id":579637286,"author":"茄酱Catsup","mid":390778601,"typeid":"136","typename":"音游","arcurl":"http://www.bilibili.com/video/av579637286","aid":579637286,"bvid":"BV1Z64y1G7gk","title":"【谱面确认/\u003cem class=\"keyword\"\u003emaimai\u003c/em\u003e/\u003cem class=\"keyword\"\u003e舞萌\u003c/em\u003e】\u003cem class=\"keyword\"\u003eヴァンパイア\u003c/em\u003e \u003cem class=\"keyword\"\u003e吸血鬼\u003c/em\u003e【紫谱】【11+】","description":"---参数---\n配速：6\n------------\n个人收藏，给自己这个大萌新练习。\n列表专供乌蒙萌新~期待大量黄铺/红谱呼你脸上。\n如无特殊说明，默认配速6\n------------\n点歌服务暂不开启。","arcrank":"0","pic":"//i2.hdslb.com/bfs/archive/9a9c67356129ffb9a902cc21b64ec98a50f73f2f.jpg","play":1392,"video_review":0,"favorites":27,"tag":"吸血鬼,音乐游戏,谱面,谱面确认,MAIMAI,舞萌,ヴァンパイア,紫谱,舞萌DX","review":2,"pubdate":1702391397,"senddate":1702391398,"duration":"2:29","badgepay":false,"hit_columns":["title","description","tag"],"view_type":"","is_pay":0,"is_union_video":0,"rec_tags":null,"new_rec_tags":[],"rank_score":111067332,"like":24,"upic":"https://i2.hdslb.com/bfs/face/b1c651238c44eb862bfc13b5a252db2e75eb6def.jpg","corner":"","cover":"","desc":"","url":"","rec_reason":"","danmaku":0,"biz_data":null,"is_charge_video":0,"vt":0,"enable_vt":0,"vt_display":"","subtitle":"","episode_count_text":"","release_status":0,"is_intervene":0},{"type":"video","id":826445184,"author":"DJNaughty","mid":27347789,"typeid":"136","typename":"音游","arcurl":"http://www.bilibili.com/video/av826445184","aid":826445184,"bvid":"BV1pg4y1c7Ft","title":"【谱面确认】【\u003cem class=\"keyword\"\u003eMAIMAI\u003c/em\u003e DX】【\u003cem class=\"keyword\"\u003eヴァンパイア\u003c/em\u003e】 Re:Master 13","description":"【谱面确认】【MAIMAI DX】【ヴァンパイア】 Re:Master 13","arcrank":"0","pic":"//i1.hdslb.com/bfs/archive/fe0e501e8ee7e32f63a99b5365a00f8aafc36d1a.png","play":35342,"video_review":2,"favorites":813,"tag":"游戏,演示,街机,音乐游戏,谱面确认,音游,maimai","review":44,"pubdate":1684800046,"senddate":1684800046,"duration":"2:30","badgepay":false,"hit_columns":["title","description","tag"],"view_type":"","is_pay":0,"is_union_video":0,"rec_tags":null,"new_rec_tags":[],"rank_score":109557861,"like":634,"upic":"https://i2.hdslb.com/bfs/face/7f883ee71f1c4beb0d744770b55bdcc78d8deace.jpg","corner":"","cover":"","desc":"","url":"","rec_reason":"","danmaku":2,"biz_data":null,"is_charge_video":0,"vt":0,"enable_vt":0,"vt_display":"","subtitle":"","episode_count_text":"","release_status":0,"is_intervene":0},{"type":"video","id":324267293,"author":"茄酱Catsup","mid":390778601,"typeid":"136","typename":"音游","arcurl":"http://www.bilibili.com/video/av324267293","aid":324267293,"bvid":"BV1qw411h7Hq","title":"【谱面确认/\u003cem class=\"keyword\"\u003emaimai\u003c/em\u003e/\u003cem class=\"keyword\"\u003e舞萌\u003c/em\u003e】\u003cem class=\"keyword\"\u003eヴァンパイア\u003c/em\u003e \u003cem class=\"keyword\"\u003e吸血鬼\u003c/em\u003e【红谱】【10】","description":"---参数---\n配速：6\n------------\n个人收藏，给自己这个大萌新练习。\n列表专供乌蒙萌新~期待大量黄铺/红谱呼你脸上。\n如无特殊说明，默认配速6\n------------\n点歌服务暂不开启。","arcrank":"0","pic":"//i2.hdslb.com/bfs/archive/6dc6d3b9bb09a3e21640b4ddf150f8503e224003.jpg","play":3726,"video_review":0,"favorites":100,"tag":"吸血鬼,音乐游戏,谱面,谱面确认,MAIMAI,舞萌,ヴァンパイア,红谱,舞萌DX","review":1,"pubdate":1701888189,"senddate":1705718390,"duration":"2:29","badgepay":false,"hit_columns":["title","description","tag"],"view_type":"","is_pay":0,"is_union_video":0,"rec_tags":null,"new_rec_tags":[],"rank_score":106805995,"like":79,"upic":"https://i2.hdslb.com/bfs/face/b1c651238c44eb862bfc13b5a252db2e75eb6def.jpg","corner":"","cover":"","desc":"","url":"","rec_reason":"","danmaku":0,"biz_data":null,"is_charge_video":0,"vt":0,"enable_vt":0,"vt_display":"","subtitle":"","episode_count_text":"","release_status":0,"is_intervene":0},{"type":"video","id":868897918,"author":"DJNaughty","mid":27347789,"typeid":"136","typename":"音游","arcurl":"http://www.bilibili.com/video/av868897918","aid":868897918,"bvid":"BV1xV4y167hV","title":"【谱面确认】【\u003cem class=\"keyword\"\u003eMAIMAI\u003c/em\u003e DX】【\u003cem class=\"keyword\"\u003eヴァンパイア\u003c/em\u003e】 Master 11+","description":"【谱面确认】【MAIMAI DX】【ヴァンパイア】 Master 11+","arcrank":"0","pic":"//i2.hdslb.com/bfs/archive/156efcd5997b727776dff6ceb6d261de3e48b92d.png","play":50936,"video_review":9,"favorites":983,"tag":"游戏,演示,街机,音乐游戏,谱面确认,音游,maimai","review":39,"pubdate":1684800044,"senddate":1684800044,"duration":"2:28","badgepay":false,"hit_columns":["title","description","tag"],"view_type":"","is_pay":0,"is_union_video":0,"rec_tags":null,"new_rec_tags":[],"rank_score":105737616,"like":585,"upic":"https://i2.hdslb.com/bfs/face/7f883ee71f1c4beb0d744770b55bdcc78d8deace.jpg","corner":"","cover":"","desc":"","url":"","rec_reason":"","danmaku":9,"biz_data":null,"is_charge_video":0,"vt":0,"enable_vt":0,"vt_display":"","subtitle":"","episode_count_text":"","release_status":0,"is_intervene":0},{"type":"video","id":530358299,"author":"Iecy_up","mid":9815795,"typeid":"136","typename":"音游","arcurl":"http://www.bilibili.com/video/av530358299","aid":530358299,"bvid":"BV1Tu411b7xC","title":"【\u003cem class=\"keyword\"\u003e舞萌\u003c/em\u003eDX2023】吸吸你的❤ \u003cem class=\"keyword\"\u003eヴァンパイア\u003c/em\u003e/\u003cem class=\"keyword\"\u003e吸血鬼\u003c/em\u003e Re：MASTER 100.9687 0-0-0 附个人拆谱","description":"加更加更！2023 6.29正式大学毕业，从此刻开始就是一个一般通过社会人了，有点感慨，虽然感到有些手足无措，但还是更个视频先~\n特别感谢@具有异能的装盐神器  画的封面~！！从此视频质量再次登上一个新台阶！其实不是所有封面都能用PS做出很好的效果来，真正的通解应该还是用手绘软件来进行修改描绘，这下有幸请到画师妈咪了(＾－＾)V\n当然，做视频主打一个不忘初心，虽然用一般的方法无法做出很好的效果来，那就不用一般的方法！直接重新构图按照以往的风格做了个封面在片尾，吸吸你们的币❤","arcrank":"0","pic":"//i1.hdslb.com/bfs/archive/98e64ac65eef1758cd7a3a5a250070a2855772f8.jpg","play":5785,"video_review":6,"favorites":68,"tag":"SEGA,音乐游戏,AP,MAIMAI,舞萌,街机音游,MAIMAI DX,舞萌DX,舞萌DX2022,音乐玩家招募令","review":145,"pubdate":1688040704,"senddate":1688052852,"duration":"2:51","badgepay":false,"hit_columns":["title","tag"],"view_type":"","is_pay":0,"is_union_video":0,"rec_tags":null,"new_rec_tags":[],"rank_score":105682770,"like":290,"upic":"https://i2.hdslb.com/bfs/face/ef0389f4b2b052d8678cc2f6c97b5a240a75ac1e.jpg","corner":"","cover":"","desc":"","url":"","rec_reason":"","danmaku":6,"biz_data":null,"is_charge_video":0,"vt":0,"enable_vt":0,"vt_display":"","subtitle":"","episode_count_text":"","release_status":0,"is_intervene":0},{"type":"video","id":234898801,"author":"敢达娘","mid":42354419,"typeid":"136","typename":"音游","arcurl":"http://www.bilibili.com/video/av234898801","aid":234898801,"bvid":"BV1je411R7pp","title":"【\u003cem class=\"keyword\"\u003e舞萌\u003c/em\u003e 紫谱11+】\u003cem class=\"keyword\"\u003eヴァンパイア\u003c/em\u003e〖MASTER AP〗","description":"ヴァンパイア （吸血鬼）\n100.9230% AP\n比较简单的紫谱，节奏很好，打起来手感很不错\n左右两侧的交互比较难，不是普通的定点交互，但放慢仔细看会发现，其实就是每组交互的第五下tap跑到了上面的按键，打的时候不要慌，看不懂容易打快，而且其中还有两组是绝赞的位移，所以一定要读好谱\n当然我不是这样打的，我纯听节奏靠感觉打。。。\n结尾最后的双押星星头后面跟着一对绝赞双押，控制速度，没有保护，不要打快","arcrank":"0","pic":"//i1.hdslb.com/bfs/archive/bb66ef491b19f736cdce7b4343aa7a18e5b5c470.jpg","play":5298,"video_review":1,"favorites":79,"tag":"VOCALOID,初音未来,DECO*27,吸血鬼,MAIMAI,ボーカロイド,音游,vampire,舞萌DX,做核酸","review":50,"pubdate":1697889600,"senddate":1697963093,"duration":"2:55","badgepay":false,"hit_columns":["title","description","tag"],"view_type":"","is_pay":0,"is_union_video":0,"rec_tags":null,"new_rec_tags":[],"rank_score":103445567,"like":168,"upic":"https://i2.hdslb.com/bfs/face/2b25d52c339e650708a78520f129f65228a010a2.jpg","corner":"","cover":"","desc":"","url":"","rec_reason":"","danmaku":1,"biz_data":null,"is_charge_video":0,"vt":0,"enable_vt":0,"vt_display":"","subtitle":"","episode_count_text":"","release_status":0,"is_intervene":0},{"type":"video","id":771914123,"author":"NICHANTAE","mid":603985663,"typeid":"136","typename":"音游","arcurl":"http://www.bilibili.com/video/av771914123","aid":771914123,"bvid":"BV1W14y1b7BQ","title":"\u003cem class=\"keyword\"\u003eヴァンパイア\u003c/em\u003e (Re:MASTER) ALL PERFECT+ [\u003cem class=\"keyword\"\u003eMaimai\u003c/em\u003e UNiVERSE+]","description":"아따 시밤 파이아~!!!","arcrank":"0","pic":"//i2.hdslb.com/bfs/archive/bbff68f626d253cad42d0b7f56e5eb207f8ad4ad.jpg","play":12885,"video_review":15,"favorites":176,"tag":"ヴァンパイア,DECO*27,MAIMAI,音乐游戏","review":72,"pubdate":1660208754,"senddate":1660281889,"duration":"2:51","badgepay":false,"hit_columns":["title","tag"],"view_type":"","is_pay":0,"is_union_video":0,"rec_tags":null,"new_rec_tags":[],"rank_score":102274788,"like":500,"upic":"http://i1.hdslb.com/bfs/face/afa0761951c0e3b20dcae8272e84c2fbbc387c0c.jpg","corner":"","cover":"","desc":"","url":"","rec_reason":"","danmaku":15,"biz_data":null,"is_charge_video":0,"vt":0,"enable_vt":0,"vt_display":"","subtitle":"","episode_count_text":"","release_status":0,"is_intervene":0},{"type":"video","id":221711832,"author":"DJNaughty","mid":27347789,"typeid":"136","typename":"音游","arcurl":"http://www.bilibili.com/video/av221711832","aid":221711832,"bvid":"BV168411H7YU","title":"【谱面确认】【\u003cem class=\"keyword\"\u003eMAIMAI\u003c/em\u003e DX】【アカツキアラ\u003cem class=\"keyword\"\u003eイヴァ\u003c/em\u003eル】 Master 13","description":"【谱面确认】【MAIMAI DX】【アカツキアライヴァル】 Master 13","arcrank":"0","pic":"//i0.hdslb.com/bfs/archive/433dfdbfe1f7096b2cf509b74a03e5f19ae79c42.png","play":2712,"video_review":0,"favorites":113,"tag":"音游,游戏,音乐游戏,街机,maimai,演示,谱面确认","review":1,"pubdate":1671872282,"senddate":1671872283,"duration":"2:44","badgepay":false,"hit_columns":[],"view_type":"","is_pay":0,"is_union_video":0,"rec_tags":null,"new_rec_tags":[],"rank_score":101423894,"like":60,"upic":"https://i2.hdslb.com/bfs/face/7f883ee71f1c4beb0d744770b55bdcc78d8deace.jpg","corner":"","cover":"","desc":"","url":"","rec_reason":"","danmaku":0,"biz_data":null,"is_charge_video":0,"vt":0,"enable_vt":0,"vt_display":"","subtitle":"","episode_count_text":"","release_status":0,"is_intervene":0},{"type":"video","id":578468992,"author":"幸运本运喵","mid":41379913,"typeid":"138","typename":"搞笑","arcurl":"http://www.bilibili.com/video/av578468992","aid":578468992,"bvid":"BV1Mz4y1A7pT","title":"【11+必打曲/红转紫/定位/交互】\u003cem class=\"keyword\"\u003eヴァンパイア\u003c/em\u003e AP \u003cem class=\"keyword\"\u003e吸血鬼\u003c/em\u003e","description":"id 11410\n个人配置\n流速：7.5\n判定2-E\n延迟：-0.1 0.1","arcrank":"0","pic":"//i0.hdslb.com/bfs/archive/54f3c85302c54d68ef635ffce056657040255605.jpg","play":6035,"video_review":103,"favorites":142,"tag":"初音未来,DECO*27,手元,MAIMAI,音游,术力口,舞萌dx,搞笑新星训练营,绿风犬三郎,搞笑研究所2023 7.0 万圣节来搞怪","review":42,"pubdate":1700099925,"senddate":1700124757,"duration":"2:25","badgepay":false,"hit_columns":["title","tag"],"view_type":"","is_pay":0,"is_union_video":0,"rec_tags":null,"new_rec_tags":[],"rank_score":101411681,"like":258,"upic":"https://i1.hdslb.com/bfs/face/0f23e8f75c656cda0e050cff5306219d3cd4579f.jpg","corner":"","cover":"","desc":"","url":"","rec_reason":"","danmaku":103,"biz_data":null,"is_charge_video":0,"vt":0,"enable_vt":0,"vt_display":"","subtitle":"","episode_count_text":"","release_status":0,"is_intervene":0},{"type":"video","id":794280795,"author":"Maybe_Somnus","mid":18139783,"typeid":"136","typename":"音游","arcurl":"http://www.bilibili.com/video/av794280795","aid":794280795,"bvid":"BV1WC4y1k76K","title":"\u003cem class=\"keyword\"\u003eヴァンパイア\u003c/em\u003e master 紫谱 纯净手元","description":"","arcrank":"0","pic":"//i1.hdslb.com/bfs/archive/26f1900fab758c42514c893f21584336abb9f732.jpg","play":366,"video_review":0,"favorites":1,"tag":"音乐游戏,手元,MAIMAI,舞萌","review":1,"pubdate":1706329625,"senddate":1706329625,"duration":"2:31","badgepay":false,"hit_columns":["title","tag"],"view_type":"","is_pay":0,"is_union_video":0,"rec_tags":null,"new_rec_tags":[],"rank_score":101387816,"like":36,"upic":"https://i1.hdslb.com/bfs/face/c8d76905d975adfdc97944e1a3b5b6f68428ced5.jpg","corner":"","cover":"","desc":"","url":"","rec_reason":"","danmaku":0,"biz_data":null,"is_charge_video":0,"vt":0,"enable_vt":0,"vt_display":"","subtitle":"","episode_count_text":"","release_status":0,"is_intervene":0},{"type":"video","id":997808266,"author":"坏困","mid":32319699,"typeid":"136","typename":"音游","arcurl":"http://www.bilibili.com/video/av997808266","aid":997808266,"bvid":"BV1qs4y1r7iX","title":"【\u003cem class=\"keyword\"\u003e舞萌\u003c/em\u003edx】\u003cem class=\"keyword\"\u003eヴァンパイア\u003c/em\u003e Re:Master 13 100.9087%","description":"great+1，菜菜","arcrank":"0","pic":"//i1.hdslb.com/bfs/archive/f9586b2e2ea8a185f8c34809c7f4f9195997113e.jpg","play":218,"video_review":0,"favorites":1,"tag":"音乐游戏,MAIMAI,ヴァンパイア,maimaidx,舞萌dx,万物皆可游戏","review":0,"pubdate":1687846188,"senddate":1704958931,"duration":"2:44","badgepay":false,"hit_columns":["title","tag"],"view_type":"","is_pay":0,"is_union_video":0,"rec_tags":null,"new_rec_tags":[],"rank_score":101274392,"like":14,"upic":"https://i0.hdslb.com/bfs/face/f703eee99809786d2ebeff133af3adfa6c07d9d0.jpg","corner":"","cover":"","desc":"","url":"","rec_reason":"","danmaku":0,"biz_data":null,"is_charge_video":0,"vt":0,"enable_vt":0,"vt_display":"","subtitle":"","episode_count_text":"","release_status":0,"is_intervene":0},{"type":"video","id":471899315,"author":"NICHANTAE","mid":603985663,"typeid":"136","typename":"音游","arcurl":"http://www.bilibili.com/video/av471899315","aid":471899315,"bvid":"BV1cT411A7cv","title":"\u003cem class=\"keyword\"\u003eヴァンパイア\u003c/em\u003e (MASTER) ALL PERFECT+ [\u003cem class=\"keyword\"\u003eMaimai\u003c/em\u003e UNiVERSE+]","description":"很开心这次的下一部作品也能欣赏到DECO的歌曲^^ \n以后remaster也请多多关照！\n아따 시밤 파이어 ww","arcrank":"0","pic":"//i0.hdslb.com/bfs/archive/19d0c48da9c7f12e266d922fbb3bd263e1b2f5fa.jpg","play":2646,"video_review":0,"favorites":30,"tag":"ヴァンパイア,DECO*27,MAIMAI,音乐游戏","review":9,"pubdate":1660197226,"senddate":1660197226,"duration":"2:49","badgepay":false,"hit_columns":["title","tag"],"view_type":"","is_pay":0,"is_union_video":0,"rec_tags":null,"new_rec_tags":[],"rank_score":101101146,"like":174,"upic":"http://i1.hdslb.com/bfs/face/afa0761951c0e3b20dcae8272e84c2fbbc387c0c.jpg","corner":"","cover":"","desc":"","url":"","rec_reason":"","danmaku":0,"biz_data":null,"is_charge_video":0,"vt":0,"enable_vt":0,"vt_display":"","subtitle":"","episode_count_text":"","release_status":0,"is_intervene":0},{"type":"video","id":573289400,"author":"自信音游人小H","mid":1190760927,"typeid":"136","typename":"音游","arcurl":"http://www.bilibili.com/video/av573289400","aid":573289400,"bvid":"BV1qz4y1J7TN","title":"【小H/\u003cem class=\"keyword\"\u003e舞萌\u003c/em\u003eDX2023】\u003cem class=\"keyword\"\u003eヴァンパイア\u003c/em\u003e  Master 11+ 99.9184%（我鸟哪去了？）","description":"视频里如果有那种像裸手搓屏幕的声音的话那应该是旁边1P的，他的手套手指处破了，绝对不是我手套破了，我这个月才买的\n\n虽然但是我的鸟没了（","arcrank":"0","pic":"//i0.hdslb.com/bfs/archive/28f7a433a7a90effd24f5e3d6a3107af92d3d467.jpg","play":268,"video_review":0,"favorites":2,"tag":"VOCALOID,FC,音乐游戏,MAIMAI","review":13,"pubdate":1689003991,"senddate":1689003991,"duration":"3:25","badgepay":false,"hit_columns":["title","tag"],"view_type":"","is_pay":0,"is_union_video":0,"rec_tags":null,"new_rec_tags":[],"rank_score":101046340,"like":8,"upic":"https://i0.hdslb.com/bfs/face/28843c9dab0d10ba1247ddd1bc9eb48dab28dcf7.jpg","corner":"","cover":"","desc":"","url":"","rec_reason":"","danmaku":0,"biz_data":null,"is_charge_video":0,"vt":0,"enable_vt":0,"vt_display":"","subtitle":"","episode_count_text":"","release_status":0,"is_intervene":0},{"type":"video","id":445249604,"author":"尘落南丘","mid":89853607,"typeid":"136","typename":"音游","arcurl":"http://www.bilibili.com/video/av445249604","aid":445249604,"bvid":"BV17j411S7jt","title":"【maimaiDX/\u003cem class=\"keyword\"\u003e舞萌\u003c/em\u003eDX】\u003cem class=\"keyword\"\u003eヴァンパイア\u003c/em\u003e Re:MASTER 13 SSS+ 100.8192","description":"","arcrank":"0","pic":"//i2.hdslb.com/bfs/archive/5302e11ad7777c382be2f30f3300d6e0ce919a84.jpg","play":271,"video_review":0,"favorites":3,"tag":"音乐游戏,MAIMAI,舞萌DX2023","review":2,"pubdate":1687599530,"senddate":1687600291,"duration":"2:42","badgepay":false,"hit_columns":["title","tag"],"view_type":"","is_pay":0,"is_union_video":0,"rec_tags":null,"new_rec_tags":[],"rank_score":100968557,"like":19,"upic":"https://i1.hdslb.com/bfs/face/1507d135ca7129b58ddf5807b8bba1bc51f0ee99.jpg","corner":"","cover":"","desc":"","url":"","rec_reason":"","danmaku":0,"biz_data":null,"is_charge_video":0,"vt":0,"enable_vt":0,"vt_display":"","subtitle":"","episode_count_text":"","release_status":0,"is_intervene":0},{"type":"video","id":879004585,"author":"-TNT233-","mid":499518249,"typeid":"136","typename":"音游","arcurl":"http://www.bilibili.com/video/av879004585","aid":879004585,"bvid":"BV1zN4y1n7Ed","title":"[\u003cem class=\"keyword\"\u003emaimai\u003c/em\u003e/红框纪念] \u003cem class=\"keyword\"\u003eヴァンパイア\u003c/em\u003e Expert 10 Rank S","description":"因视频录制角度原因，可能出现频繁遮挡镜头的情况，敬请谅解！","arcrank":"0","pic":"//i0.hdslb.com/bfs/archive/bba8fb9add42334be59edb467993ec1488007369.jpg","play":125,"video_review":0,"favorites":0,"tag":"音乐游戏,MAIMAI,舞萌,必剪创作,舞萌dx2024","review":1,"pubdate":1705859217,"senddate":1705859218,"duration":"2:42","badgepay":false,"hit_columns":["title","tag"],"view_type":"","is_pay":0,"is_union_video":0,"rec_tags":null,"new_rec_tags":[],"rank_score":100920601,"like":4,"upic":"https://i0.hdslb.com/bfs/face/35b3d1426d47acd2e1e5c0f2bfddcab6dc2d0206.jpg","corner":"","cover":"","desc":"","url":"","rec_reason":"","danmaku":0,"biz_data":null,"is_charge_video":0,"vt":0,"enable_vt":0,"vt_display":"","subtitle":"","episode_count_text":"","release_status":0,"is_intervene":0},{"type":"video","id":212564040,"author":"unumo","mid":433666626,"typeid":"136","typename":"音游","arcurl":"http://www.bilibili.com/video/av212564040","aid":212564040,"bvid":"BV1Ra411t79U","title":"【\u003cem class=\"keyword\"\u003emaimai\u003c/em\u003e外部出力】\u003cem class=\"keyword\"\u003eヴァンパイア\u003c/em\u003e(\u003cem class=\"keyword\"\u003e吸血鬼\u003c/em\u003e) 白AP+(理论值)【谱面确认】","description":"(Player:unumo)\n\n推特\n(http://twitter.com/unumo0917)","arcrank":"0","pic":"//i2.hdslb.com/bfs/archive/16953adb7fbe9113291b46d1d8ec5e745e9683a2.jpg","play":16063,"video_review":0,"favorites":337,"tag":"音游,maimai,ヴァンパイア,吸血鬼,DECO*27,初音未来","review":14,"pubdate":1648277530,"senddate":1648277530,"duration":"2:57","badgepay":false,"hit_columns":["title","tag"],"view_type":"","is_pay":0,"is_union_video":0,"rec_tags":null,"new_rec_tags":[],"rank_score":100814253,"like":247,"upic":"https://i0.hdslb.com/bfs/face/8eeda0729a81193a2ea908dc30d7dd495cfea3ab.jpg","corner":"","cover":"","desc":"","url":"","rec_reason":"","danmaku":0,"biz_data":null,"is_charge_video":0,"vt":0,"enable_vt":0,"vt_display":"","subtitle":"","episode_count_text":"","release_status":0,"is_intervene":0},{"type":"video","id":749418221,"author":"Komeiji-Akatsuki","mid":167511896,"typeid":"136","typename":"音游","arcurl":"http://www.bilibili.com/video/av749418221","aid":749418221,"bvid":"BV1sC4y1w73M","title":"\u003cem class=\"keyword\"\u003eヴァンパイア\u003c/em\u003e（\u003cem class=\"keyword\"\u003e吸血鬼\u003c/em\u003e）白谱 100.84（内录+外录）手元","description":"当前版本定数13.4\n感觉比定数要更加简单\n由于在刷AP的时候出现了手癖..所以不再尝试\n\n开始有一段..轴交互？hold不动位置另外一只手逐渐转圈..很慢\n140combo建议及时换手...换到自己惯用手的位置\n之后的难点在于休息段之后的下楼梯..右手二号键起手\n结尾那一段如果手容易miss的话..可以试着把身体侧过来..这样会好一些\n\n和上一次是同一首歌..但这次的难度相对更高\n不过由于在刷AP的时候出现了手癖..所以短期不再尝试了","arcrank":"0","pic":"//i2.hdslb.com/bfs/archive/e115707936c4d586b384a0ff597191f296eee488.jpg","play":1732,"video_review":0,"favorites":12,"tag":"初音未来,DECO*27,吸血鬼,舞萌,ヴァンパイア,萌新,maimai,舞萌dx","review":4,"pubdate":1702016505,"senddate":1702016505,"duration":"2:44","badgepay":false,"hit_columns":["title","tag"],"view_type":"","is_pay":0,"is_union_video":0,"rec_tags":null,"new_rec_tags":[],"rank_score":100810525,"like":41,"upic":"https://i2.hdslb.com/bfs/face/1fa13d2fb7b69d28b426d19acbb13e239931cbbb.jpg","corner":"","cover":"","desc":"","url":"","rec_reason":"","danmaku":0,"biz_data":null,"is_charge_video":0,"vt":0,"enable_vt":0,"vt_display":"","subtitle":"","episode_count_text":"","release_status":0,"is_intervene":0},{"type":"video","id":663945582,"author":"H4mmer","mid":3494349188893550,"typeid":"136","typename":"音游","arcurl":"http://www.bilibili.com/video/av663945582","aid":663945582,"bvid":"BV15a4y1f7mx","title":"\u003cem class=\"keyword\"\u003eヴァンパイア\u003c/em\u003e Re:Master难度 手顺参考","description":"声明：本视频出现的手顺并不完全是官方手顺，部分手顺采用了敝人自己的手顺见解，还请见谅\n没有绝对正确的手序，只有最适合自己的手顺。\n\n视频中出现的红色tap/星星/touch为右手，蓝色tap/星星/touch为左手\n\n\n白开水\n欢迎点歌，在能力范围内的都会尝试做的。本首为@北北official  点歌","arcrank":"0","pic":"//i1.hdslb.com/bfs/archive/3960d70bc165d8e56578e718246dc4368057311f.jpg","play":2951,"video_review":0,"favorites":78,"tag":"DECO*27,吸血鬼,教学,音乐游戏,MAIMAI,参考,ヴァンパイア,Re:Master,舞萌DX,手顺","review":12,"pubdate":1701147600,"senddate":1701441510,"duration":"2:15","badgepay":false,"hit_columns":["title","tag"],"view_type":"","is_pay":0,"is_union_video":0,"rec_tags":null,"new_rec_tags":[],"rank_score":100797374,"like":214,"upic":"https://i2.hdslb.com/bfs/face/22210ff9a5aaaa008f89ac802633d064895fac55.jpg","corner":"","cover":"","desc":"","url":"","rec_reason":"","danmaku":0,"biz_data":null,"is_charge_video":0,"vt":0,"enable_vt":0,"vt_display":"","subtitle":"","episode_count_text":"","release_status":0,"is_intervene":0}]}],"is_search_page_grayed":0}}